syft_tensorflow/__init__.py
syft_tensorflow/attributes/__init__.py
syft_tensorflow/attributes/attributes.py
syft_tensorflow/hook/__init__.py
syft_tensorflow/hook/hook.py
syft_tensorflow/hook/hook_args.py
syft_tensorflow/serde/__init__.py
syft_tensorflow/serde/serde.py
syft_tensorflow/serde/serde_test.py
syft_tensorflow/syft_types/__init__.py
syft_tensorflow/syft_types/keras_layer.py
syft_tensorflow/syft_types/keras_layers_test.py
syft_tensorflow/syft_types/keras_model.py
syft_tensorflow/syft_types/keras_model_test.py
syft_tensorflow/syft_types/keras_object.py
syft_tensorflow/syft_types/tensor.py
syft_tensorflow/syft_types/tensor_test.py
syft_tensorflow/syft_types/variable.py
syft_tensorflow/syft_types/variable_test.py
syft_tensorflow/tensor/__init__.py
syft_tensorflow/tensor/tensor.py
test/__init__.py
test/serde_test.py
test/tensor_test.py
syft_tensorflow-0.1.0.dist-info/LICENSE
syft_tensorflow-0.1.0.dist-info/METADATA
syft_tensorflow-0.1.0.dist-info/WHEEL
syft_tensorflow-0.1.0.dist-info/top_level.txt
syft_tensorflow-0.1.0.dist-info/RECORD
