Metadata-Version: 2.1
Name: syft-tensorflow
Version: 0.1.0
Summary: TensorFlow Bindings for PySyft
Home-page: https://github.com/OpenMined/PySyft-TensorFlow
Author: OpenMined
Author-email: contact@openmined.org
License: Apache-2.0
Keywords: deep learning artificial intelligence privacy secure multi-party computation federated learning differential privacy
Platform: UNKNOWN
Classifier: Programming Language :: Python :: 3
Classifier: Operating System :: OS Independent
Requires-Dist: tensorflow (>=2.0.0-rc2)
